pg_resourceloader/__init__.py
pg_resourceloader/define.py
pg_resourceloader/loader.py
pg_resourceloader/loader_manager.py
pg_resourceloader-1.0.5.dist-info/METADATA
pg_resourceloader-1.0.5.dist-info/WHEEL
pg_resourceloader-1.0.5.dist-info/top_level.txt
pg_resourceloader-1.0.5.dist-info/RECORD
