Metadata-Version: 2.1
Name: pg_resourceloader
Version: 1.0.5
Summary: python game: resourceloader
Author: baozilaji@gmail.com
Requires-Python: >=3.9
Requires-Dist: pg-environment
Requires-Dist: pg-objectserialization
